py_tools/__init__.py
py_tools/play.py
py_tools-0.0.0.dist-info/DESCRIPTION.rst
py_tools-0.0.0.dist-info/METADATA
py_tools-0.0.0.dist-info/RECORD
py_tools-0.0.0.dist-info/WHEEL
py_tools-0.0.0.dist-info/metadata.json
py_tools-0.0.0.dist-info/top_level.txt
