Metadata-Version: 2.0
Name: py-tools
Version: 0.0.0
Summary: Important tools for Python
Home-page: https://github.com/kevinjuan25/kevinjuan25_py_tools
Author: Kevin Juan
Author-email: kj89@cornell.edu
License: MIT
Platform: UNKNOWN
Requires-Dist: matplotlib
Requires-Dist: numpy
Requires-Dist: pandas
Requires-Dist: pint
Requires-Dist: scipy
